{
  "$schema": "file:///C:/lectron/schemas/ServerMetaSchema.schema.json",
  "meta": {
    "version": "1.0.0",
    "name": "lectron (Minecraft 1.16.5)",
    "description": "lectron Running Minecraft 1.16.5 (Forge v36.1.24)",
    "address": "localhost:25565",
    "discord": {
      "shortId": "<FILL IN OR REMOVE DISCORD OBJECT>",
      "largeImageText": "<FILL IN OR REMOVE DISCORD OBJECT>",
      "largeImageKey": "<FILL IN OR REMOVE DISCORD OBJECT>"
    },
    "mainServer": false,
    "autoconnect": false
  },
  "forge": {
    "version": "36.1.24"
  },
  "untrackedFiles": []
}